LICENSE
MANIFEST.in
README.rst
setup.cfg
setup.py
sphinxsharp/__init__.py
sphinxsharp/sphinxsharp.py
sphinxsharp.egg-info/PKG-INFO
sphinxsharp.egg-info/SOURCES.txt
sphinxsharp.egg-info/dependency_links.txt
sphinxsharp.egg-info/requires.txt
sphinxsharp.egg-info/top_level.txt
sphinxsharp/locales/ru/LC_MESSAGES/sphinxsharp.po