Metadata-Version: 2.1
Name: sphinxsharp
Version: 1.0.2
Summary: CSharp (C#) domain for sphinx.
Home-page: https://github.com/madTeddy/sphinxsharp
Author: Andrey Mignevich
Author-email: andrey.mignevich@gmail.com
License: MIT
Download-URL: https://github.com/madTeddy/sphinxsharp/archive/refs/tags/v1.0.2.tar.gz
Keywords: Documentation,Sphinx,Domain,CSharp,C#,Sphinxsharp
Platform: UNKNOWN
Classifier: Development Status :: 5 - Production/Stable
Classifier: Intended Audience :: Developers
Classifier: Topic :: Documentation :: Sphinx
Classifier: License :: OSI Approved :: MIT License
Classifier: Programming Language :: Python :: 3
Classifier: Programming Language :: Python :: 3.4
Classifier: Programming Language :: Python :: 3.5
Classifier: Programming Language :: Python :: 3.6
Classifier: Programming Language :: Python :: 3.7
Classifier: Programming Language :: Python :: 3.8
Classifier: Programming Language :: Python :: 3.9
